awil_mcp3802/__init__.py
awil_mcp3802/awil_mcp3802.py
awil_mcp3802-0.1.2.dist-info/LICENSE
awil_mcp3802-0.1.2.dist-info/METADATA
awil_mcp3802-0.1.2.dist-info/WHEEL
awil_mcp3802-0.1.2.dist-info/top_level.txt
awil_mcp3802-0.1.2.dist-info/RECORD
