Metadata-Version: 2.1
Name: awil_mcp3802
Version: 0.1.2
Author: Noriki Mochizuki
Author-email: noriki.mochizuki.mj@gmail.com
License: MIT
License-File: LICENSE
Requires-Dist: awil-ft232h
